Metadata-Version: 2.1
Name: yake
Version: 0.4.7
Summary: Keyword extraction Python package
Home-page: https://pypi.python.org/pypi/yake
License: LGPLv3
Keywords: yake
Platform: UNKNOWN
Classifier: Development Status :: 3 - Alpha
Classifier: License :: OSI Approved :: GNU General Public License v3 (GPLv3)
Classifier: Programming Language :: Python :: 3
Classifier: Programming Language :: Python :: 3.5
Classifier: Programming Language :: Python :: 3.6
Classifier: Programming Language :: Python :: 3.7
Classifier: Programming Language :: Python :: 3.8
Classifier: Topic :: Scientific/Engineering :: Information Analysis
Classifier: Topic :: Software Development :: Libraries
Classifier: Topic :: Text Processing
Classifier: Topic :: Text Processing :: Linguistic
Requires-Dist: tabulate
Requires-Dist: click (>=6.0)
Requires-Dist: numpy
Requires-Dist: segtok
Requires-Dist: networkx
Requires-Dist: jellyfish
